poster_design/__init__.py
poster_design/__version__.py
poster_design/assets/backgrounds/README.md
poster_design/assets/backgrounds/blue_1.jpeg
poster_design/assets/backgrounds/blue_2.jpeg
poster_design/assets/backgrounds/blue_3.jpeg
poster_design/assets/backgrounds/blue_4.jpeg
poster_design/assets/backgrounds/blue_5.jpeg
poster_design/assets/backgrounds/blue_6.jpeg
poster_design/assets/backgrounds/blue_7.jpeg
poster_design/assets/backgrounds/blue_8.jpeg
poster_design/assets/backgrounds/colorful_1.jpeg
poster_design/assets/backgrounds/colorful_2.jpeg
poster_design/assets/backgrounds/colorful_3.jpeg
poster_design/assets/backgrounds/colorful_4.jpeg
poster_design/assets/backgrounds/colorful_5.jpeg
poster_design/assets/backgrounds/dark_1.jpeg
poster_design/assets/backgrounds/dark_blue_1.jpeg
poster_design/assets/backgrounds/dark_green_1.jpeg
poster_design/assets/backgrounds/dark_green_2.jpeg
poster_design/assets/backgrounds/green_1.jpg
poster_design/assets/backgrounds/green_2.jpeg
poster_design/assets/backgrounds/green_3.jpeg
poster_design/assets/backgrounds/green_4.jpeg
poster_design/assets/backgrounds/green_5.jpeg
poster_design/assets/backgrounds/green_6.jpeg
poster_design/assets/backgrounds/green_7.jpeg
poster_design/assets/backgrounds/green_8.jpeg
poster_design/assets/backgrounds/orange_1.jpeg
poster_design/assets/backgrounds/pink_1.jpeg
poster_design/assets/backgrounds/pink_2.jpeg
poster_design/assets/backgrounds/pink_3.jpeg
poster_design/assets/backgrounds/pink_4.jpeg
poster_design/assets/backgrounds/pink_5.jpeg
poster_design/assets/backgrounds/white_1.jpeg
poster_design/core/__init__.py
poster_design/core/backgrounds.py
poster_design/core/canvas.py
poster_design/core/elements.py
poster_design/core/filters.py
poster_design/core/layout.py
poster_design/core/manager.py
poster_design/core/models.py
poster_design/core/positioning.py
poster_design/core/presets.py
poster_design/core/styles.py
poster_design/mcp/__init__.py
poster_design/mcp/handlers.py
poster_design-0.1.0.dist-info/licenses/LICENSE
poster_design-0.1.0.dist-info/METADATA
poster_design-0.1.0.dist-info/WHEEL
poster_design-0.1.0.dist-info/entry_points.txt
poster_design-0.1.0.dist-info/top_level.txt
poster_design-0.1.0.dist-info/RECORD
