Metadata-Version: 2.4
Name: poster-design
Version: 0.1.0
Summary: A powerful poster design library with optional MCP integration for LLM agents
Author: Poster Design Contributors
License: MIT
Project-URL: Homepage, https://github.com/Zts0hg/poster-design
Project-URL: Documentation, https://github.com/Zts0hg/poster-design#readme
Project-URL: Repository, https://github.com/Zts0hg/poster-design
Project-URL: Issues, https://github.com/Zts0hg/poster-design/issues
Project-URL: Changelog, https://github.com/Zts0hg/poster-design/blob/main/CHANGELOG.md
Keywords: poster,design,graphics,image-generation,mcp,llm,agent,ai
Classifier: Development Status :: 3 - Alpha
Classifier: Intended Audience :: Developers
Classifier: License :: OSI Approved :: MIT License
Classifier: Programming Language :: Python :: 3
Classifier: Programming Language :: Python :: 3.9
Classifier: Programming Language :: Python :: 3.10
Classifier: Programming Language :: Python :: 3.11
Classifier: Programming Language :: Python :: 3.12
Classifier: Topic :: Multimedia :: Graphics
Classifier: Topic :: Software Development :: Libraries :: Python Modules
Requires-Python: >=3.9
License-File: LICENSE
Requires-Dist: pillow>=10.0.0
Requires-Dist: pydantic>=2.0.0
Requires-Dist: typing-extensions>=4.0.0
Provides-Extra: mcp
Requires-Dist: mcp>=0.1.0; extra == "mcp"
Requires-Dist: aiohttp>=3.9.0; extra == "mcp"
Provides-Extra: dev
Requires-Dist: pytest>=7.4.0; extra == "dev"
Requires-Dist: pytest-asyncio>=0.21.0; extra == "dev"
Requires-Dist: pytest-cov>=4.1.0; extra == "dev"
Requires-Dist: pytest-mock>=3.12.0; extra == "dev"
Requires-Dist: black>=23.0.0; extra == "dev"
Requires-Dist: ruff>=0.1.0; extra == "dev"
Requires-Dist: mypy>=1.5.0; extra == "dev"
Requires-Dist: pre-commit>=3.4.0; extra == "dev"
Provides-Extra: docs
Requires-Dist: mkdocs>=1.5.0; extra == "docs"
Requires-Dist: mkdocs-material>=9.4.0; extra == "docs"
Requires-Dist: mkdocstrings[python]>=0.23.0; extra == "docs"
Provides-Extra: test
Requires-Dist: pytest>=7.4.0; extra == "test"
Requires-Dist: pytest-asyncio>=0.21.0; extra == "test"
Requires-Dist: pytest-cov>=4.1.0; extra == "test"
Requires-Dist: pytest-mock>=3.12.0; extra == "test"
Provides-Extra: all
Requires-Dist: poster-design[mcp]; extra == "all"
Requires-Dist: poster-design[dev]; extra == "all"
Requires-Dist: poster-design[docs]; extra == "all"
Dynamic: license-file
